trajectify/ConstrainedState.py
trajectify/Path.py
trajectify/Pose.py
trajectify/QuinticSpline.py
trajectify/Robot.py
trajectify/State.py
trajectify/Trajectory.py
trajectify/__init__.py
trajectify/constrained_state.py
trajectify/trajectify_classes.py
trajectify-0.0.6.dist-info/LICENSE
trajectify-0.0.6.dist-info/METADATA
trajectify-0.0.6.dist-info/WHEEL
trajectify-0.0.6.dist-info/top_level.txt
trajectify-0.0.6.dist-info/RECORD
